{
    "name": "1.0_Deactivate Google Forms",
    "flow": [
        {
            "id": 5,
            "module": "gateway:CustomWebHook",
            "version": 1,
            "parameters": {
                "hook": 838159,
                "maxResults": 1
            },
            "mapper": {},
            "metadata": {
                "designer": {
                    "x": 16,
                    "y": -220
                },
                "restore": {
                    "parameters": {
                        "hook": {
                            "data": {
                                "editable": "true"
                            },
                            "label": "Deactivate Google Forms"
                        }
                    }
                },
                "parameters": [
                    {
                        "name": "hook",
                        "type": "hook:gateway-webhook",
                        "label": "Webhook",
                        "required": true
                    },
                    {
                        "name": "maxResults",
                        "type": "number",
                        "label": "Maximum number of results"
                    }
                ]
            }
        },
        {
            "id": 3,
            "module": "http:ActionSendData",
            "version": 3,
            "parameters": {
                "handleErrors": false,
                "useNewZLibDeCompress": true
            },
            "mapper": {
                "ca": "",
                "qs": [],
                "url": "https://digibp.herokuapp.com/engine-rest/external-task/fetchAndLock",
                "data": "{\n  \"workerId\":\"IntegromatWorker\",\n  \"maxTasks\":1,\n  \"asyncResponseTimeout\":29000,\n  \"topics\":[\n    {\n      \"topicName\":\"Deactivate Google Forms\",\n      \"lockDuration\":20000,\n      \"tenantId\":\"peaches\"\n    }\n  ]\n}",
                "gzip": true,
                "method": "post",
                "headers": [],
                "timeout": "",
                "useMtls": false,
                "authPass": "",
                "authUser": "",
                "bodyType": "raw",
                "contentType": "application/json",
                "serializeUrl": false,
                "shareCookies": false,
                "parseResponse": true,
                "followRedirect": true,
                "useQuerystring": false,
                "followAllRedirects": false,
                "rejectUnauthorized": true
            },
            "metadata": {
                "designer": {
                    "x": 383,
                    "y": -216
                },
                "restore": {
                    "expect": {
                        "qs": {
                            "mode": "chose"
                        },
                        "method": {
                            "mode": "chose",
                            "label": "POST"
                        },
                        "headers": {
                            "mode": "chose"
                        },
                        "bodyType": {
                            "label": "Raw"
                        },
                        "contentType": {
                            "label": "JSON (application/json)"
                        }
                    }
                },
                "parameters": [
                    {
                        "name": "handleErrors",
                        "type": "boolean",
                        "label": "Evaluate all states as errors (except for 2xx and 3xx )",
                        "required": true
                    },
                    {
                        "name": "useNewZLibDeCompress",
                        "type": "hidden"
                    }
                ],
                "expect": [
                    {
                        "name": "url",
                        "type": "url",
                        "label": "URL",
                        "required": true
                    },
                    {
                        "name": "serializeUrl",
                        "type": "boolean",
                        "label": "Serialize URL",
                        "required": true
                    },
                    {
                        "name": "method",
                        "type": "select",
                        "label": "Method",
                        "required": true,
                        "validate": {
                            "enum": [
                                "get",
                                "head",
                                "post",
                                "put",
                                "patch",
                                "delete",
                                "options"
                            ]
                        }
                    },
                    {
                        "name": "headers",
                        "spec": [
                            {
                                "name": "name",
                                "type": "text",
                                "label": "Name",
                                "required": true
                            },
                            {
                                "name": "value",
                                "type": "text",
                                "label": "Value"
                            }
                        ],
                        "type": "array",
                        "label": "Headers"
                    },
                    {
                        "name": "qs",
                        "spec": [
                            {
                                "name": "name",
                                "type": "text",
                                "label": "Name",
                                "required": true
                            },
                            {
                                "name": "value",
                                "type": "text",
                                "label": "Value"
                            }
                        ],
                        "type": "array",
                        "label": "Query String"
                    },
                    {
                        "name": "bodyType",
                        "type": "select",
                        "label": "Body type",
                        "validate": {
                            "enum": [
                                "raw",
                                "x_www_form_urlencoded",
                                "multipart_form_data"
                            ]
                        }
                    },
                    {
                        "name": "parseResponse",
                        "type": "boolean",
                        "label": "Parse response",
                        "required": true
                    },
                    {
                        "name": "authUser",
                        "type": "text",
                        "label": "User name"
                    },
                    {
                        "name": "authPass",
                        "type": "password",
                        "label": "Password"
                    },
                    {
                        "name": "timeout",
                        "type": "uinteger",
                        "label": "Timeout",
                        "validate": {
                            "max": 300,
                            "min": 1
                        }
                    },
                    {
                        "name": "shareCookies",
                        "type": "boolean",
                        "label": "Share cookies with other HTTP modules",
                        "required": true
                    },
                    {
                        "name": "ca",
                        "type": "cert",
                        "label": "Self-signed certificate"
                    },
                    {
                        "name": "rejectUnauthorized",
                        "type": "boolean",
                        "label": "Reject connections that are using unverified (self-signed) certificates",
                        "required": true
                    },
                    {
                        "name": "followRedirect",
                        "type": "boolean",
                        "label": "Follow redirect",
                        "required": true
                    },
                    {
                        "name": "useQuerystring",
                        "type": "boolean",
                        "label": "Disable serialization of multiple same query string keys as arrays",
                        "required": true
                    },
                    {
                        "name": "gzip",
                        "type": "boolean",
                        "label": "Request compressed content",
                        "required": true
                    },
                    {
                        "name": "useMtls",
                        "type": "boolean",
                        "label": "Use Mutual TLS",
                        "required": true
                    },
                    {
                        "name": "contentType",
                        "type": "select",
                        "label": "Content type",
                        "validate": {
                            "enum": [
                                "text/plain",
                                "application/json",
                                "application/xml",
                                "text/xml",
                                "text/html",
                                "custom"
                            ]
                        }
                    },
                    {
                        "name": "data",
                        "type": "buffer",
                        "label": "Request content"
                    },
                    {
                        "name": "followAllRedirects",
                        "type": "boolean",
                        "label": "Follow all redirect",
                        "required": true
                    }
                ]
            }
        },
        {
            "id": 7,
            "module": "google-forms:trashForm",
            "version": 2,
            "parameters": {
                "__IMTCONN__": 1432127
            },
            "mapper": {
                "formId": "{{3.data[].variables.Wage_request_form_ID.value}}"
            },
            "metadata": {
                "designer": {
                    "x": 683,
                    "y": -216
                },
                "restore": {
                    "parameters": {
                        "__IMTCONN__": {
                            "data": {
                                "scoped": "true",
                                "connection": "google"
                            },
                            "label": "add-pizza (digital.juicy.peaches@gmail.com)"
                        }
                    }
                },
                "parameters": [
                    {
                        "name": "__IMTCONN__",
                        "type": "account:google",
                        "label": "Connection",
                        "required": true
                    }
                ],
                "expect": [
                    {
                        "name": "formId",
                        "type": "text",
                        "label": "Form ID",
                        "required": true
                    }
                ]
            }
        },
        {
            "id": 8,
            "module": "google-sheets:filterRows",
            "version": 2,
            "parameters": {
                "__IMTCONN__": 1432127
            },
            "mapper": {
                "from": "drive",
                "limit": "1",
                "filter": [
                    [
                        {
                            "a": "H",
                            "b": "{{3.data[].variables.Application_sheet_id.value}}",
                            "o": "text:equal"
                        }
                    ]
                ],
                "sheetId": "Jobs",
                "sortOrder": "asc",
                "spreadsheetId": "197RX1XnaCF0_PAIPL5jEVysyBgGWDWEYiQUUs0UJqf0",
                "tableFirstRow": "A1:Z1",
                "includesHeaders": true,
                "valueRenderOption": "FORMATTED_VALUE",
                "dateTimeRenderOption": "FORMATTED_STRING"
            },
            "metadata": {
                "designer": {
                    "x": 982,
                    "y": -214
                },
                "restore": {
                    "expect": {
                        "from": {
                            "label": "Select from My Drive"
                        },
                        "orderBy": {
                            "mode": "chose"
                        },
                        "sheetId": {
                            "mode": "chose",
                            "label": "Jobs"
                        },
                        "sortOrder": {
                            "mode": "chose",
                            "label": "Ascending"
                        },
                        "spreadsheetId": {
                            "mode": "chose",
                            "label": "PublishedJobsInformation"
                        },
                        "tableFirstRow": {
                            "label": "A-Z"
                        },
                        "includesHeaders": {
                            "mode": "chose",
                            "label": "Yes"
                        },
                        "valueRenderOption": {
                            "mode": "chose",
                            "label": "Formatted value"
                        },
                        "dateTimeRenderOption": {
                            "mode": "chose",
                            "label": "Formatted string"
                        }
                    },
                    "parameters": {
                        "__IMTCONN__": {
                            "data": {
                                "scoped": "true",
                                "connection": "google"
                            },
                            "label": "add-pizza (digital.juicy.peaches@gmail.com)"
                        }
                    }
                },
                "parameters": [
                    {
                        "name": "__IMTCONN__",
                        "type": "account:google",
                        "label": "Connection",
                        "required": true
                    }
                ],
                "expect": [
                    {
                        "name": "from",
                        "type": "select",
                        "label": "Enter a Spreadsheet ID and Sheet Name",
                        "required": true,
                        "validate": {
                            "enum": [
                                "drive",
                                "share"
                            ]
                        }
                    },
                    {
                        "name": "valueRenderOption",
                        "type": "select",
                        "label": "Value render option",
                        "validate": {
                            "enum": [
                                "FORMATTED_VALUE",
                                "UNFORMATTED_VALUE",
                                "FORMULA"
                            ]
                        }
                    },
                    {
                        "name": "dateTimeRenderOption",
                        "type": "select",
                        "label": "Date and time render option",
                        "validate": {
                            "enum": [
                                "SERIAL_NUMBER",
                                "FORMATTED_STRING"
                            ]
                        }
                    },
                    {
                        "name": "limit",
                        "type": "number",
                        "label": "Maximum number of returned rows"
                    },
                    {
                        "name": "spreadsheetId",
                        "type": "select",
                        "label": "Spreadsheet",
                        "required": true
                    },
                    {
                        "name": "sheetId",
                        "type": "select",
                        "label": "Sheet Name",
                        "required": true
                    },
                    {
                        "name": "includesHeaders",
                        "type": "select",
                        "label": "Table contains headers",
                        "required": true,
                        "validate": {
                            "enum": [
                                true,
                                false
                            ]
                        }
                    },
                    {
                        "name": "tableFirstRow",
                        "type": "select",
                        "label": "Column range",
                        "required": true,
                        "validate": {
                            "enum": [
                                "A1:Z1",
                                "A1:BZ1",
                                "A1:CZ1",
                                "A1:DZ1",
                                "A1:MZ1",
                                "A1:ZZ1",
                                "A1:AZZ1",
                                "A1:BZZ1",
                                "A1:CZZ1",
                                "A1:DZZ1",
                                "A1:MZZ1",
                                "A1:ZZZ1"
                            ]
                        }
                    },
                    {
                        "name": "filter",
                        "type": "filter",
                        "label": "Filter",
                        "options": "rpc://google-sheets/2/rpcGetFilterKeys?includesHeaders=true"
                    },
                    {
                        "name": "sortOrder",
                        "type": "select",
                        "label": "Sort order",
                        "validate": {
                            "enum": [
                                "asc",
                                "desc"
                            ]
                        }
                    },
                    {
                        "name": "orderBy",
                        "type": "select",
                        "label": "Order by"
                    }
                ],
                "interface": [
                    {
                        "name": "__IMTLENGTH__",
                        "type": "uinteger",
                        "label": "Total number of bundles"
                    },
                    {
                        "name": "__IMTINDEX__",
                        "type": "uinteger",
                        "label": "Bundle order position"
                    },
                    {
                        "name": "__ROW_NUMBER__",
                        "type": "number",
                        "label": "Row number"
                    },
                    {
                        "name": "__SPREADSHEET_ID__",
                        "type": "text",
                        "label": "Spreadsheet ID"
                    },
                    {
                        "name": "__SHEET__",
                        "type": "text",
                        "label": "Sheet"
                    },
                    {
                        "name": "0",
                        "type": "text",
                        "label": "Job Title (A)"
                    },
                    {
                        "name": "1",
                        "type": "text",
                        "label": "Job ID (B)"
                    },
                    {
                        "name": "2",
                        "type": "text",
                        "label": "Wage Grade (C)"
                    },
                    {
                        "name": "3",
                        "type": "text",
                        "label": "Office Location (D)"
                    },
                    {
                        "name": "4",
                        "type": "text",
                        "label": "Form Link (E)"
                    },
                    {
                        "name": "5",
                        "type": "text",
                        "label": "Folder Link (F)"
                    },
                    {
                        "name": "6",
                        "type": "text",
                        "label": "Application Sheet Link (G)"
                    },
                    {
                        "name": "7",
                        "type": "text",
                        "label": "Application Sheet ID (H)"
                    },
                    {
                        "name": "8",
                        "type": "text",
                        "label": "Application Deadline (I)"
                    },
                    {
                        "name": "9",
                        "type": "text",
                        "label": "Job Description (J)"
                    },
                    {
                        "name": "10",
                        "type": "text",
                        "label": "Application Window (K)"
                    },
                    {
                        "name": "11",
                        "type": "text",
                        "label": "(L)"
                    },
                    {
                        "name": "12",
                        "type": "text",
                        "label": "(M)"
                    },
                    {
                        "name": "13",
                        "type": "text",
                        "label": "(N)"
                    },
                    {
                        "name": "14",
                        "type": "text",
                        "label": "(O)"
                    },
                    {
                        "name": "15",
                        "type": "text",
                        "label": "(P)"
                    },
                    {
                        "name": "16",
                        "type": "text",
                        "label": "(Q)"
                    },
                    {
                        "name": "17",
                        "type": "text",
                        "label": "(R)"
                    },
                    {
                        "name": "18",
                        "type": "text",
                        "label": "(S)"
                    },
                    {
                        "name": "19",
                        "type": "text",
                        "label": "(T)"
                    },
                    {
                        "name": "20",
                        "type": "text",
                        "label": "(U)"
                    },
                    {
                        "name": "21",
                        "type": "text",
                        "label": "(V)"
                    },
                    {
                        "name": "22",
                        "type": "text",
                        "label": "(W)"
                    },
                    {
                        "name": "23",
                        "type": "text",
                        "label": "(X)"
                    },
                    {
                        "name": "24",
                        "type": "text",
                        "label": "(Y)"
                    },
                    {
                        "name": "25",
                        "type": "text",
                        "label": "(Z)"
                    }
                ]
            }
        },
        {
            "id": 9,
            "module": "google-sheets:updateCell",
            "version": 2,
            "parameters": {
                "__IMTCONN__": 1432127
            },
            "mapper": {
                "cell": "K{{8.`__ROW_NUMBER__`}}",
                "from": "drive",
                "value": "Closed",
                "select": "list",
                "sheetId": "Jobs",
                "spreadsheetId": "/1vco45Dk82Q6CT5dmS9EiTRSB95owGH8W/1SQSXuBtdaKg0sSNhWnVQwXwIBSGCA0Rb/197RX1XnaCF0_PAIPL5jEVysyBgGWDWEYiQUUs0UJqf0",
                "valueInputOption": "USER_ENTERED"
            },
            "metadata": {
                "designer": {
                    "x": 1267,
                    "y": -204
                },
                "restore": {
                    "expect": {
                        "from": {
                            "label": "My Drive"
                        },
                        "select": {
                            "label": "Select from the list"
                        },
                        "sheetId": {
                            "label": "Jobs"
                        },
                        "spreadsheetId": {
                            "path": [
                                "Job Advertisements",
                                "01_Administration",
                                "PublishedJobsInformation"
                            ]
                        },
                        "valueInputOption": {
                            "mode": "chose",
                            "label": "User entered"
                        }
                    },
                    "parameters": {
                        "__IMTCONN__": {
                            "data": {
                                "scoped": "true",
                                "connection": "google"
                            },
                            "label": "add-pizza (digital.juicy.peaches@gmail.com)"
                        }
                    }
                },
                "parameters": [
                    {
                        "name": "__IMTCONN__",
                        "type": "account:google",
                        "label": "Connection",
                        "required": true
                    }
                ],
                "expect": [
                    {
                        "name": "select",
                        "type": "select",
                        "label": "Enter a Spreadsheet and Sheet ID",
                        "required": true,
                        "validate": {
                            "enum": [
                                "map",
                                "fromAll",
                                "list"
                            ]
                        }
                    },
                    {
                        "name": "cell",
                        "type": "text",
                        "label": "Cell",
                        "required": true
                    },
                    {
                        "name": "value",
                        "type": "text",
                        "label": "Value"
                    },
                    {
                        "name": "valueInputOption",
                        "type": "select",
                        "label": "Value input option",
                        "validate": {
                            "enum": [
                                "USER_ENTERED",
                                "RAW"
                            ]
                        }
                    },
                    {
                        "name": "from",
                        "type": "select",
                        "label": "Choose a Drive",
                        "required": true,
                        "validate": {
                            "enum": [
                                "drive",
                                "share",
                                "team"
                            ]
                        }
                    },
                    {
                        "name": "spreadsheetId",
                        "type": "file",
                        "label": "Spreadsheet ID",
                        "required": true
                    },
                    {
                        "name": "sheetId",
                        "type": "select",
                        "label": "Sheet Name",
                        "required": true
                    }
                ]
            }
        },
        {
            "id": 4,
            "module": "http:ActionSendData",
            "version": 3,
            "parameters": {
                "handleErrors": false,
                "useNewZLibDeCompress": true
            },
            "mapper": {
                "ca": "",
                "qs": [],
                "url": "https://digibp.herokuapp.com/engine-rest/external-task/{{3.data[].id}}/complete",
                "data": "{\n  \"workerId\":\"IntegromatWorker\",\n  \"variables\":{\n  }\n}",
                "gzip": true,
                "method": "post",
                "headers": [],
                "timeout": "",
                "useMtls": false,
                "authPass": "",
                "authUser": "",
                "bodyType": "raw",
                "contentType": "application/json",
                "serializeUrl": false,
                "shareCookies": false,
                "parseResponse": true,
                "followRedirect": true,
                "useQuerystring": false,
                "followAllRedirects": false,
                "rejectUnauthorized": true
            },
            "metadata": {
                "designer": {
                    "x": 1553,
                    "y": -219
                },
                "restore": {
                    "expect": {
                        "qs": {
                            "mode": "chose"
                        },
                        "method": {
                            "mode": "chose",
                            "label": "POST"
                        },
                        "headers": {
                            "mode": "chose"
                        },
                        "bodyType": {
                            "label": "Raw"
                        },
                        "contentType": {
                            "label": "JSON (application/json)"
                        }
                    }
                },
                "parameters": [
                    {
                        "name": "handleErrors",
                        "type": "boolean",
                        "label": "Evaluate all states as errors (except for 2xx and 3xx )",
                        "required": true
                    },
                    {
                        "name": "useNewZLibDeCompress",
                        "type": "hidden"
                    }
                ],
                "expect": [
                    {
                        "name": "url",
                        "type": "url",
                        "label": "URL",
                        "required": true
                    },
                    {
                        "name": "serializeUrl",
                        "type": "boolean",
                        "label": "Serialize URL",
                        "required": true
                    },
                    {
                        "name": "method",
                        "type": "select",
                        "label": "Method",
                        "required": true,
                        "validate": {
                            "enum": [
                                "get",
                                "head",
                                "post",
                                "put",
                                "patch",
                                "delete",
                                "options"
                            ]
                        }
                    },
                    {
                        "name": "headers",
                        "spec": [
                            {
                                "name": "name",
                                "type": "text",
                                "label": "Name",
                                "required": true
                            },
                            {
                                "name": "value",
                                "type": "text",
                                "label": "Value"
                            }
                        ],
                        "type": "array",
                        "label": "Headers"
                    },
                    {
                        "name": "qs",
                        "spec": [
                            {
                                "name": "name",
                                "type": "text",
                                "label": "Name",
                                "required": true
                            },
                            {
                                "name": "value",
                                "type": "text",
                                "label": "Value"
                            }
                        ],
                        "type": "array",
                        "label": "Query String"
                    },
                    {
                        "name": "bodyType",
                        "type": "select",
                        "label": "Body type",
                        "validate": {
                            "enum": [
                                "raw",
                                "x_www_form_urlencoded",
                                "multipart_form_data"
                            ]
                        }
                    },
                    {
                        "name": "parseResponse",
                        "type": "boolean",
                        "label": "Parse response",
                        "required": true
                    },
                    {
                        "name": "authUser",
                        "type": "text",
                        "label": "User name"
                    },
                    {
                        "name": "authPass",
                        "type": "password",
                        "label": "Password"
                    },
                    {
                        "name": "timeout",
                        "type": "uinteger",
                        "label": "Timeout",
                        "validate": {
                            "max": 300,
                            "min": 1
                        }
                    },
                    {
                        "name": "shareCookies",
                        "type": "boolean",
                        "label": "Share cookies with other HTTP modules",
                        "required": true
                    },
                    {
                        "name": "ca",
                        "type": "cert",
                        "label": "Self-signed certificate"
                    },
                    {
                        "name": "rejectUnauthorized",
                        "type": "boolean",
                        "label": "Reject connections that are using unverified (self-signed) certificates",
                        "required": true
                    },
                    {
                        "name": "followRedirect",
                        "type": "boolean",
                        "label": "Follow redirect",
                        "required": true
                    },
                    {
                        "name": "useQuerystring",
                        "type": "boolean",
                        "label": "Disable serialization of multiple same query string keys as arrays",
                        "required": true
                    },
                    {
                        "name": "gzip",
                        "type": "boolean",
                        "label": "Request compressed content",
                        "required": true
                    },
                    {
                        "name": "useMtls",
                        "type": "boolean",
                        "label": "Use Mutual TLS",
                        "required": true
                    },
                    {
                        "name": "contentType",
                        "type": "select",
                        "label": "Content type",
                        "validate": {
                            "enum": [
                                "text/plain",
                                "application/json",
                                "application/xml",
                                "text/xml",
                                "text/html",
                                "custom"
                            ]
                        }
                    },
                    {
                        "name": "data",
                        "type": "buffer",
                        "label": "Request content"
                    },
                    {
                        "name": "followAllRedirects",
                        "type": "boolean",
                        "label": "Follow all redirect",
                        "required": true
                    }
                ]
            }
        }
    ],
    "metadata": {
        "instant": true,
        "version": 1,
        "scenario": {
            "roundtrips": 1,
            "maxErrors": 3,
            "autoCommit": true,
            "autoCommitTriggerLast": true,
            "sequential": false,
            "confidential": false,
            "dataloss": false,
            "dlq": false,
            "freshVariables": false
        },
        "designer": {
            "orphans": []
        },
        "zone": "eu1.make.com"
    }
}